hmeg/__init__.py
hmeg/entities.py
hmeg/exercise_generator.py
hmeg/grammar_checker.py
hmeg/miniphrase/ab.toml
hmeg/miniphrase/cd.toml
hmeg/miniphrase/efg.toml
hmeg/miniphrase/h.toml
hmeg/miniphrase/ikl.toml
hmeg/miniphrase/mn.toml
hmeg/miniphrase/opr.toml
hmeg/miniphrase/stu.toml
hmeg/miniphrase/wy.toml
hmeg/registry.py
hmeg/reranker.py
hmeg/topics/1_basic_present_tense.toml
hmeg/topics/1_from_a_to_b_from_c_until_d.toml
hmeg/topics/1_have_dont_have_there_is_there_isnt.toml
hmeg/topics/1_i_want_to.toml
hmeg/topics/1_negative_sentenses.toml
hmeg/topics/1_past_tense.toml
hmeg/topics/1_please_give_me.toml
hmeg/topics/1_this_is.toml
hmeg/topics/1_topic_subject_particle.toml
hmeg/topics/1_what_do_you_want_to_do.toml
hmeg/topics/2_and_and_then_therefore_so.toml
hmeg/topics/2_and_with.toml
hmeg/topics/2_but_however.toml
hmeg/topics/2_can_cannot.toml
hmeg/topics/2_dont_do_it.toml
hmeg/topics/2_future_tense.toml
hmeg/topics/2_have_to_should_must.toml
hmeg/topics/2_if_in_case.toml
hmeg/topics/2_imperative.toml
hmeg/topics/2_particles_for_method_way.toml
hmeg/topics/2_please_do_it_for_me.toml
hmeg/topics/2_present_progressive.toml
hmeg/topics/2_to_be_good_poor_at.toml
hmeg/topics/2_to_like.toml
hmeg/topics/3_after_ing.toml
hmeg/topics/3_approximately_about.toml
hmeg/topics/3_before_ing.toml
hmeg/topics/3_but_still_nevertheless.toml
hmeg/topics/3_even_if_even_though.toml
hmeg/topics/3_in_front_of_behind.toml
hmeg/topics/3_in_order_to_for_the_sake_of.toml
hmeg/topics/3_linking_verbs_고.toml
hmeg/topics/3_linking_verbs_여서.toml
hmeg/topics/3_linking_words_는데.toml
hmeg/topics/3_maybe_i_might.toml
hmeg/topics/3_nothing_but_only.toml
hmeg/topics/3_shall_we_i_wonder.toml
hmeg/topics/3_to_look_like_seem_like.toml
hmeg/topics/3_too_much_very.toml
hmeg/topics/3_verb_ending_네요.toml
hmeg/topics/3_well_then_in_that_case.toml
hmeg/topics/4_among_between.toml
hmeg/topics/4_do_you_want_to.toml
hmeg/topics/4_i_think_past_future.toml
hmeg/topics/4_it_cant_be.toml
hmeg/topics/4_it_is_ok_to.toml
hmeg-0.1.6.dist-info/LICENSE
hmeg-0.1.6.dist-info/METADATA
hmeg-0.1.6.dist-info/WHEEL
hmeg-0.1.6.dist-info/RECORD
