Metadata-Version: 2.3
Name: hmeg
Version: 0.1.6
Summary: Generator of exercises for practicing speaking for language learning.
License: MIT
Author: Yury Choi
Author-email: yurytsoy@gmail.com
Requires-Python: >=3.9,<3.14
Classifier: License :: OSI Approved :: MIT License
Classifier: Programming Language :: Python :: 3
Classifier: Programming Language :: Python :: 3.9
Classifier: Programming Language :: Python :: 3.10
Classifier: Programming Language :: Python :: 3.11
Classifier: Programming Language :: Python :: 3.12
Classifier: Programming Language :: Python :: 3.13
Requires-Dist: fire (>=0.6.0,<0.7.0)
Requires-Dist: inflect (>=7.0.0,<8.0.0)
Requires-Dist: kenlm (>=0.3.0,<0.4.0)
Requires-Dist: language-tool-python (>=2.9.4,<3.0.0)
Requires-Dist: nltk (>=3.8.1,<4.0.0)
Requires-Dist: numpy (>=2.0.0,<3.0.0)
Requires-Dist: pandas (>=2.2.2,<3.0.0)
Requires-Dist: python-levenshtein (>=0.27.1,<0.28.0)
Requires-Dist: sentencepiece (>=0.2.1,<0.3.0)
Requires-Dist: spacy (>=3.8.7,<4.0.0)
Requires-Dist: toml (>=0.10.2,<0.11.0)
Requires-Dist: torch (>=2.8.0,<3.0.0)
Requires-Dist: torchvision (>=0.23.0,<0.24.0)
Requires-Dist: transformers (>=4.56.1,<5.0.0)
Project-URL: Repository, https://github.com/yurytsoy/hmeg
